Workbook

Sheet Resource Catalog
A1: Resource | B1: Category | C1: Tier | D1: Rarity | E1: Tone | F1: Primary Sources | G1: Primary Uses | H1: Design Purpose | I1: Example Buildings/Systems | J1: Cozy Use | K1: Horror Use | L1: Early Game | M1: Mid Game | N1: Late Game | O1: Related BuildableEffects | P1: Notes
A2: Coins | B2: Core Economy | C2: Early | D2: Common | E2: Cozy | F2: Sell crops, complete requests, trade goods, festival rewards | G2: Buy seeds, tools, upgrades, buildings, animal feed, cosmetics | H2: Main economic currency. Keeps the cozy farming loop familiar and easy to understand. | I2: Market Stall, General Store, Carpenter, Seed Shop | J2: Earned through ordinary farming and town requests. | K2: Can purchase harmless-looking items that later feed into ritual systems. | L2: Primary progression currency. | M2: Still useful for expansion and convenience. | N2: Less important than ritual resources, but still needed for town-facing systems. | O2: GenerateCurrencyEffect; ShopDiscountEffect; TownRequestRewardEffect | P2: Coins should never become useless, but should stop being the only meaningful gate.
A3: Blood Essence | B3: Blood / Ritual | C3: Mid | D3: Uncommon | E3: Horror | F3: Bloodroot, Blood Well, sacrifices, night rituals, living structures | G3: Living buildings, guardian mutations, ritual upgrades, forbidden tools | H3: Secondary power currency that asks the player to engage with darker systems. | I3: Bloodroot Altar, Blood Well, Root Cathedral | J3: Functions like a magical fertilizer or rare crafting essence at first. | K3: Revealed as life force harvested through increasingly unsettling methods. | L3: Rare and mysterious. | M3: Unlocks the darker progression track. | N3: Primary resource for eldritch structures and high-tier rituals. | O3: GenerateBloodEssenceEffect; RitualPowerEffect; GuardianMutationEffect | P3: This is the main bridge between cozy farming and cozy horror.
A4: Favor | B4: Core Economy | C4: Early | D4: Uncommon | E4: Mixed | F4: Help townsfolk, complete seasonal events, spare creatures, fulfill offerings | G4: Unlock vendors, story branches, discounts, town projects | H4: Social progression resource that can contrast against darker ritual choices. | I4: Town Board, Shrine of Thanks, Community Garden | J4: Earned by helping people and improving the town. | K4: Can be spent to hide suspicious garden activity or gain trust. | L4: Unlocks social systems. | M4: Competes with blood-based choices. | N4: Supports endings and relationship outcomes. | O4: GenerateFavorEffect; RelationshipBoostEffect | P4: Useful if you want the player to balance public kindness with private horror.
A5: Wood | B5: Building | C5: Early | D5: Common | E5: Cozy | F5: Trees, fallen logs, forest gathering, lumberyard | G5: Fences, workbenches, storage, basic buildings, paths | H5: Basic construction material. Gives the player immediate agency over expansion. | I5: Shed, Fence, Compost Bin, Storage Chest | J5: Standard building material from chopping trees. | K5: Later variants may come from living trees or cursed groves. | L5: Constantly used for basic structures. | M5: Used in upgraded buildings and crafting stations. | N5: Replaced by Heartwood for living structures. | O5: BuildCostReductionEffect; StructureUpgradeEffect | P5: Keep high demand early so exploration and gathering feel meaningful.
A6: Stone | B6: Building | C6: Early | D6: Common | E6: Cozy | F6: Rocks, quarry, caves, ruins | G6: Foundations, wells, walls, altars, paths | H6: Durable construction material that supports permanent-feeling upgrades. | I6: Well, Stone Path, Root Cellar, Altar Base | J6: Used for sturdy farm structures. | K6: Used for altars, grave markers, ritual circles, and sealed chambers. | L6: Basic construction and paths. | M6: Ritual structures and wells. | N6: Ancient stone variants appear in ruins. | O6: DefenseBoostEffect; RitualStructureEffect | P6: Pairs well with bones and moss for graveyard architecture.
A7: Fiber | B7: Building | C7: Early | D7: Common | E7: Cozy | F7: Tall grass, reeds, vines, crop scraps | G7: Rope, cloth, bindings, simple tools, scarecrows | H7: Soft crafting material that links farming, foraging, and basic utility. | I7: Scarecrow, Drying Rack, Loom, Binding Totem | J7: Craft rope, bags, fabric, and decorations. | K7: Used as ritual bindings and restraints for living structures. | L7: Basic crafting. | M7: Used in charms and ritual components. | N7: Upgraded into Living Vine or sinewy bindings. | O7: CraftingUtilityEffect; RitualBindingEffect | P7: A good resource to make weeds feel useful instead of annoying.
A8: Clay | B8: Building | C8: Early | D8: Common | E8: Cozy | F8: Riverbanks, ponds, muddy fields, swamp nodes | G8: Pots, bricks, kiln recipes, irrigation pieces | H8: Supports crafting progression and encourages visiting wet biomes. | I8: Kiln, Planter Pots, Irrigation Channels | J8: Pottery, planters, and cute decorations. | K8: Can become cursed clay for doll-like effigies and sealed vessels. | L8: Planters and small crafting. | M8: Kiln upgrades and alchemy containers. | N8: Used for ritual urns and spirit vessels. | O8: ContainerCraftingEffect; DecorationValueEffect | P8: Good for making the river/swamp area mechanically valuable.
A9: Iron Ore | B9: Building | C9: Mid | D9: Uncommon | E9: Cozy | F9: Mines, caves, rare rock nodes, trader | G9: Tool upgrades, machinery, gates, pumps, reinforced buildings | H9: Signals the move from basic farming into more advanced systems. | I9: Forge, Pump, Reinforced Fence, Mechanical Mill | J9: Tool and building upgrades. | K9: Iron can bind spirits, lock cages, or reinforce containment structures. | L9: Rare. | M9: Major upgrade resource. | N9: Used with occult materials for containment and automation. | O9: ToolUpgradeEffect; AutomationEffect; ContainmentEffect | P9: Great midpoint between cozy tech and dark containment mechanics.
A10: Glass | B10: Building | C10: Mid | D10: Uncommon | E10: Cozy | F10: Smelt sand, salvage from ruins, trade | G10: Greenhouses, jars, lenses, lanterns, alchemy containers | H10: Unlocks controlled growing environments and nighttime lighting systems. | I10: Greenhouse, Jar Shelf, Lens Tower, Lantern Posts | J10: Greenhouses and decorative jars. | K10: Observation chambers, preserved organs, specimen jars, blood tanks. | L10: Not available or rare. | M10: Greenhouse progression. | N10: Used in eldritch laboratories and containment rooms. | O10: GreenhouseBoostEffect; PreservationEffect; LightRadiusEffect | P10: Very useful for making cozy visuals subtly creepy.
A11: Seeds | B11: Farming | C11: Early | D11: Common | E11: Cozy | F11: Seed shop, harvested crops, wild plants, quest rewards | G11: Grow crops, unlock strains, feed living buildings | H11: The backbone of the farming loop and player planning. | I11: Seed Shop, Seed Dryer, Seed Vault | J11: Plant crops and expand the farm. | K11: Some seeds may twitch, whisper, or require blood to germinate. | L11: Core loop. | M11: Specialized crops and mutations. | N11: Rare living seeds and eldritch strains. | O11: SpawnSeedEffect; SeedDuplicationEffect; CropMutationEffect | P11: Seed variety drives replayability and seasonal planning.
A12: Vegetables | B12: Farming | C12: Early | D12: Common | E12: Cozy | F12: Farm plots, greenhouse, town market | G12: Food, selling, cooking, sacrifices, animal feed | H12: Main crop output and flexible resource for economy and rituals. | I12: Kitchen, Market Stall, Harvest Shrine | J12: Sell, cook, gift, and complete requests. | K12: Sacrifice entire harvests for buffs or feed carnivorous plants. | L12: Main income. | M12: Ingredient in cooking and ritual recipes. | N12: Bulk sacrifice and high-volume production. | O12: CropYieldEffect; HarvestSacrificeEffect | P12: Keep vegetable crops emotionally familiar before making them ritual fuel.
... A52: Starlit Dew | B52: Rare / Legendary | C52: Late | D52: Rare | E52: Cozy | F52: Clear nights, celestial flowers, dew collectors, lunar events | G52: Gentle high-tier potions, crop quality, calming guardians | H52: Balances late-game horror with beautiful, peaceful resources. | I52: Dew Collector, Celestial Garden, Spirit Lantern | J52: Magical dew collected under stars. | K52: Can calm creatures that should not be alive. | L52: Not available. | M52: Rare event reward. | N52: Premium calming and quality resource. | O52: CropQualityBoostEffect; GuardianCalmEffect; SpiritCleanseEffect | P52: Important for keeping the tone from becoming only grim.

Sheet Categories
A1: Category | B1: Design Role | C1: Example Resources | D1: Resource Count
A2: Core Economy | B2: Currencies and social progression resources that guide broad player advancement. | C2: Coins, Blood Essence, Favor | D2: =COUNTIF('Resource Catalog'!$B:$B,A2) -> 2
A3: Building | B3: Physical construction materials used to expand and upgrade the farm. | C3: Wood, Stone, Fiber, Clay, Iron Ore, Glass | D3: =COUNTIF('Resource Catalog'!$B:$B,A3) -> 6
A4: Farming | B4: Resources grown through crops, flowers, herbs, orchards, and soil systems. | C4: Seeds, Vegetables, Fruits, Herbs, Flowers, Fertilizer | D4: =COUNTIF('Resource Catalog'!$B:$B,A4) -> 6
A5: Foraging | B5: Resources gathered from the surrounding wilderness, forests, ruins, and wetlands. | C5: Berries, Mushrooms, Moss, Wild Honey, Wild Roots | D5: =COUNTIF('Resource Catalog'!$B:$B,A5) -> 5
A6: Animal | B6: Ranching, hunting, and creature-based products. | C6: Animal Hide, Feathers, Meat, Milk, Eggs, Wool | D6: =COUNTIF('Resource Catalog'!$B:$B,A6) -> 6
A7: Decay | B7: Resources created from death, rot, spoiled crops, graves, and remains. | C7: Rot, Bones, Grave Moss, Spirit Ash, Corpse Wax | D7: =COUNTIF('Resource Catalog'!$B:$B,A7) -> 5
A8: Blood / Ritual | B8: Life-force and ritual-focused resources that push the horror progression. | C8: Blood Essence, Bloodroot | D8: =COUNTIF('Resource Catalog'!$B:$B,A8) -> 2
A9: Living | B9: Materials harvested from living buildings, mutated plants, or plant-creatures. | C9: Heartwood, Living Vine, Bloom Flesh, Seed Cores, Black Sap | D9: =COUNTIF('Resource Catalog'!$B:$B,A9) -> 5
A10: Guardian | B10: Resources used to grow, evolve, and specialize plant guardians. | C10: Guardian Seeds, Mutation Spores, Growth Nectar, Thorn Plates | D10: =COUNTIF('Resource Catalog'!$B:$B,A10) -> 4
A11: Ritual | B11: Ingredients used for offerings, magical infrastructure, inscriptions, and lunar systems. | C11: Candles, Moonwater, Ritual Ink, Ancient Bark, Offering Tokens | D11: =COUNTIF('Resource Catalog'!$B:$B,A11) -> 5
A12: Rare / Legendary | B12: High-impact resources tied to major upgrades, story beats, and endings. | C12: Heartfruit, Elder Root, Lunar Petals, Void Seeds, Starlit Dew | D12: =COUNTIF('Resource Catalog'!$B:$B,A12) -> 5

Sheet Progression Flow
A1: Stage | B1: Key Resources | C1: Player Feeling | D1: Design Goal
A2: Early Game | B2: Wood, Stone, Fiber, Seeds, Berries, Mushrooms, Moss, Flowers, Milk, Eggs, Coins | C2: Feels like a cozy farming sim. The player learns gathering, planting, selling, and simple crafting. | D2: Build a home base, plant crops, meet town systems, establish daily rhythm.
A3: Early → Mid Transition | B3: Herbs, Fertilizer, Clay, Feathers, Wild Roots, Offering Tokens, rare Bloodroot | C3: The world starts becoming strange but still approachable. | D3: Introduce rituals gently without overwhelming the cozy loop.
A4: Mid Game | B4: Iron Ore, Glass, Rot, Bones, Bloodroot, Blood Essence, Moonwater, Ritual Ink, Guardian Seeds | C4: The player begins making darker choices and engaging with night systems. | D4: Unlock living buildings, sacrifices, guardian growth, and ritual networks.
A5: Mid → Late Transition | B5: Grave Moss, Spirit Ash, Mutation Spores, Living Vine, Growth Nectar, Black Sap | C5: The farm becomes partially alive and death becomes productive. | D5: Turn base building into ecosystem design with specialized production chains.
A6: Late Game | B6: Heartwood, Bloom Flesh, Seed Cores, Ancient Bark, Lunar Petals, Heartfruit, Elder Root, Void Seeds | C6: The player fully embraces cozy horror farming. | D6: Support endgame structures, major rituals, guardian ascension, and story endings.

Sheet Gameplay Loops
A1: Loop | B1: Resource Flow | C1: Game Design Purpose
A2: Cozy Farming Loop | B2: Plant Seeds → Grow Crops → Harvest Vegetables/Fruits → Sell for Coins → Buy upgrades | C2: Keeps the game grounded and familiar.
A3: Foraging Loop | B3: Explore Woods → Gather Berries/Mushrooms/Moss → Cook, craft, or trade | C3: Encourages daily exploration and biome variety.
A4: Decay Loop | B4: Crops Spoil or Creatures Die → Create Rot/Bones → Compost or Ritual Use → Boost Growth | C4: Turns failure and death into useful progression.
A5: Blood Ritual Loop | B5: Grow Bloodroot or Sacrifice Resources → Gain Blood Essence → Unlock Living Buildings/Rituals | C5: Core horror progression path.
A6: Night Production Loop | B6: Prepare during Day → Activate Moon/Night Buildings → Collect Moonwater/Lunar Petals/Blood bonuses | C6: Makes time of day strategically meaningful.
A7: Living Building Loop | B7: Obtain Seed Core → Grow Building → Feed with Blood/Rot/Nectar → Unlock new production | C7: Creates emotional investment in structures.
A8: Guardian Loop | B8: Find Guardian Seed → Grow Defender → Feed Nectar/Spores → Mutate or Evolve | C8: Makes defense feel like pet/creature raising.
A9: Ritual Network Loop | B9: Place related structures → Connect network → Trigger bonus effects or combined rituals | C9: Turns base layout into a planning puzzle.

Sheet Summary
A1: The Garden Resource Ecosystem
A3: This workbook maps the resource economy for The Garden, starting with cozy farming materials like wood, stone, seeds, berries, mushrooms, moss, and animal products, then gradually moving into rot, bones, Blood Essence, living plant materials, guardians, and ritual networks.
A7: Category | B7: Count | D7: Tier | E7: Count
A8: Core Economy | B8: =COUNTIF('Resource Catalog'!$B:$B,A8) -> 2 | D8: Early | E8: =COUNTIF('Resource Catalog'!$C:$C,D8) -> 23
A9: Building | B9: =COUNTIF('Resource Catalog'!$B:$B,A9) -> 6 | D9: Mid | E9: =COUNTIF('Resource Catalog'!$C:$C,D9) -> 16
A10: Farming | B10: =COUNTIF('Resource Catalog'!$B:$B,A10) -> 6 | D10: Late | E10: =COUNTIF('Resource Catalog'!$C:$C,D10) -> 12
A11: Foraging | B11: =COUNTIF('Resource Catalog'!$B:$B,A11) -> 5
A12: Animal | B12: =COUNTIF('Resource Catalog'!$B:$B,A12) -> 6
A13: Decay | B13: =COUNTIF('Resource Catalog'!$B:$B,A13) -> 5
A14: Blood / Ritual | B14: =COUNTIF('Resource Catalog'!$B:$B,A14) -> 2
A15: Living | B15: =COUNTIF('Resource Catalog'!$B:$B,A15) -> 5
A16: Guardian | B16: =COUNTIF('Resource Catalog'!$B:$B,A16) -> 4
A17: Ritual | B17: =COUNTIF('Resource Catalog'!$B:$B,A17) -> 5
A18: Rare / Legendary | B18: =COUNTIF('Resource Catalog'!$B:$B,A18) -> 5
